hawa/__init__.py
hawa/base/__init__.py
hawa/base/db.py
hawa/base/decos.py
hawa/base/errors.py
hawa/base/init.py
hawa/common/__init__.py
hawa/common/data.py
hawa/common/query.py
hawa/common/utils.py
hawa/config.py
hawa/data/__init__.py
hawa/data/assemble.py
hawa/data/city.py
hawa/data/district.py
hawa/data/group.py
hawa/data/klass.py
hawa/data/province.py
hawa/data/school.py
hawa/data/student.py
hawa/paper/__init__.py
hawa/paper/health.py
hawa/paper/mht.py
hawadata-0.17.4.dist-info/WHEEL
hawadata-0.17.4.dist-info/METADATA
hawadata-0.17.4.dist-info/RECORD
