Metadata-Version: 2.3
Name: hawadata
Version: 0.17.4
Summary: Add your description here
Requires-Dist: databases
Requires-Dist: decorator
Requires-Dist: loguru
Requires-Dist: munch
Requires-Dist: mysqlclient
Requires-Dist: numpy
Requires-Dist: pandas
Requires-Dist: pendulum
Requires-Dist: pingouin>=0.5.5
Requires-Dist: pydantic
Requires-Dist: pymysql
Requires-Dist: redis
Requires-Dist: requests
Requires-Dist: scikit-learn>=1.7.1
Requires-Dist: scipy
Requires-Dist: seaborn
Requires-Dist: setuptools
Requires-Dist: sqlalchemy
Requires-Python: >=3.10
